Partie-1/2_Hardware/Etape_3/vivado/pgcd 2.vhd
library IEEE;
use IEEE.STD_LOGIC_1164.ALL;
use IEEE.NUMERIC_STD.ALL;

ENTITY PGCD IS
PORT 
( 
	CLK      : in  STD_LOGIC;
	RESET    : in  STD_LOGIC;

	idata_a  : in  STD_LOGIC_VECTOR (31 downto 0);
	idata_b  : in  STD_LOGIC_VECTOR (31 downto 0);
	idata_en : in  STD_LOGIC;

	odata    : out STD_LOGIC_VECTOR (31 downto 0);
	odata_en : out STD_LOGIC
);
END PGCD;

architecture Behavioral of PGCD is
    TYPE STATE_TYPE IS (init, compute, output);
    SIGNAL current_state, next_state : STATE_TYPE;
    
    signal A     : signed(31 downto 0);
    signal B     : signed(31 downto 0);
    signal A1    : signed(31 downto 0);
    signal B1    : signed(31 downto 0);

begin
    --State register
    PROCESS (CLK, RESET)
    BEGIN
        IF RESET = '1' THEN
            current_state  <= init;
        ELSIF (CLK'EVENT AND CLK = '1') THEN
            current_state <= next_state;
        END IF;
    END PROCESS;

    --next state
    PROCESS(current_state, A, B)
    begin
        case current_state is
            when init => 
                if (idata_en = '1') THEN
                    --inputs asserts
                    assert (A >= 0) report "idata_a < 0" severity failure;
                    assert (B >= 0) report "idata_b < 0" severity failure;
                    assert (A <= 65535) report "idata_a > 65535" severity failure;
                    assert (B <= 65535) report "idata_b > 65535" severity failure;
                    
                    A1 <= signed(idata_a);
                    B1 <= signed(idata_b);
                    next_state <= compute;
                else 
                    next_state <= current_state;
                end if;
                
            when compute =>
                --assert (idata_en = '0') report "Load while computing" severity failure;
                
                if (A = B) then
                    next_state <= output;
                else
                    next_state <= current_state;
                end if;
                    
            when output => 
                --outputs asserts
                assert (idata_en = '0') report "Load while getting outputs" severity failure;
                --assert (A1 >= A) report "Output bigger than input" severity failure;
                --assert (B1 >= B) report "Output bigger than input" severity failure;
                assert (A >= 0) report "Negative output" severity failure;
                next_state <= init;
        end case;
    end process;

    --output
    process(current_state, A)
    begin
        case current_state is
            when init | compute =>  odata_en    <= '0';
                                    odata       <= std_logic_vector(A);
                        
            when output =>          odata_en    <= '1';
                                    odata       <= std_logic_vector(A);
        end case;
    end process;

    --compute pgcd
    process(CLK, RESET, current_state)
    begin
        IF (RESET = '1') THEN
            A   <= (others => '0');
            B   <= (others => '0');
            A1  <= (others => '0');
            B1  <= (others => '0');

        elsif (current_state = init) then
            A  <= signed(idata_a);
            B  <= signed(idata_b);
            A1 <= signed(idata_a);
            B1 <= signed(idata_b);

        ELSIF (CLK'EVENT AND CLK = '1' AND current_state = compute) THEN
            if (A = 0) then
                A <= B;
            elsif (B = 0) then
                B <= A;
            elsif (A > B) then 
                A <= A - B;
            elsif (B > A) then 
                B <= B - A;
            end if;
        end if;
    end process;

end Behavioral;

Partie-1/2_Hardware/Etape_2/vivado/pgcd_tb 2.vhd
library IEEE;
use IEEE.Std_logic_1164.all;
use IEEE.Numeric_Std.all;

entity PGCD_tb is
end;

architecture bench of PGCD_tb is

    component PGCD
    PORT 
    ( 
        CLK      : in  STD_LOGIC;
        RESET    : in  STD_LOGIC;
        idata_a  : in  STD_LOGIC_VECTOR (31 downto 0);
        idata_b  : in  STD_LOGIC_VECTOR (31 downto 0);
        idata_en : in  STD_LOGIC;
        odata    : out STD_LOGIC_VECTOR (31 downto 0);
        odata_en : out STD_LOGIC
    );
    end component;

    signal CLK: STD_LOGIC;
    signal RESET: STD_LOGIC;
    signal idata_a: STD_LOGIC_VECTOR (31 downto 0);
    signal idata_b: STD_LOGIC_VECTOR (31 downto 0);
    signal idata_en: STD_LOGIC;
    signal odata: STD_LOGIC_VECTOR (31 downto 0);
    signal odata_en: STD_LOGIC ;

    constant clock_period: time := 10 ns;
    signal stop_the_clock: boolean;

begin

    uut: PGCD port map ( CLK      => CLK,
                        RESET    => RESET,
                        idata_a  => idata_a,
                        idata_b  => idata_b,
                        idata_en => idata_en,
                        odata    => odata,
                        odata_en => odata_en );

    stimulus: process
    begin
    
        -- Put initialisation code here
        idata_a <= (others => '0');
        idata_b <= (others => '0');
        idata_en <= '0';

        RESET <= '1';
        wait for 5 ns;
        RESET <= '0';
        wait for 5 ns;

        idata_en <= '1';
        idata_a <= std_logic_vector(to_signed(0, idata_a'length));
        idata_b <= std_logic_vector(to_signed(10, idata_b'length));
        wait for clock_period;
        while odata_en = '0' loop
            idata_en <= '0';
            wait for 10 ns;
        end loop;
        ASSERT SIGNED( odata )= TO_SIGNED(10, 32) SEVERITY ERROR;

        idata_en <= '1';
        idata_a <= std_logic_vector(to_signed(10, idata_a'length));
        idata_b <= std_logic_vector(to_signed(0, idata_b'length));
        wait for clock_period;
        while odata_en = '0' loop
            idata_en <= '0';
            wait for 10 ns;
        end loop;
        ASSERT SIGNED( odata ) = TO_SIGNED(10, 32)  SEVERITY ERROR;

        idata_en <= '1';
        idata_a <= std_logic_vector(to_signed(40, idata_a'length));
        idata_b <= std_logic_vector(to_signed(24, idata_b'length));
        wait for clock_period;
        while odata_en = '0' loop
            idata_en <= '0';
            wait for 10 ns;
        end loop;
        ASSERT SIGNED( odata ) = TO_SIGNED(8, 32) SEVERITY ERROR;

        idata_en <= '1';
        idata_a <= std_logic_vector(to_signed(24, idata_a'length));
        idata_b <= std_logic_vector(to_signed(40, idata_b'length));
        wait for clock_period;
        while odata_en = '0' loop
            idata_en <= '0';
            wait for 10 ns;
        end loop;
        ASSERT SIGNED( odata ) = TO_SIGNED(8, 32) SEVERITY ERROR;

        idata_en <= '1';
        idata_a <= std_logic_vector(to_signed(7, idata_a'length));
        idata_b <= std_logic_vector(to_signed(13, idata_b'length));
        wait for clock_period;
        while odata_en = '0' loop
            idata_en <= '0';
            wait for 10 ns;
        end loop;
        ASSERT SIGNED( odata ) = TO_SIGNED(1, 32) SEVERITY ERROR;
        
        idata_en <= '1';
        idata_a <= std_logic_vector(to_signed(0, idata_a'length));
        idata_b <= std_logic_vector(to_signed(0, idata_b'length));
        wait for clock_period;
        while odata_en = '0' loop
            idata_en <= '0';
            wait for 10 ns;
        end loop;
        ASSERT SIGNED( odata ) = TO_SIGNED(0, 32) SEVERITY ERROR;

        wait for 200 ns;
        stop_the_clock <= true;
        wait;
    end process;

    clocking: process
    begin
        while not stop_the_clock loop
        CLK <= '0', '1' after clock_period / 2;
        wait for clock_period;
        end loop;
        wait;
    end process;

end;

Partie-1/2_Hardware/Etape_7/signaux 2.vcd
$date
  Wed Oct 13 11:13:01 2021
$end
$version
  GHDL v0
$end
$timescale
  1 fs
$end
$scope module standard $end
$upscope $end
$scope module std_logic_1164 $end
$upscope $end
$scope module numeric_std $end
$upscope $end
$scope module pgcd_tb $end
$var reg 1 ! clk $end
$var reg 1 " reset $end
$var reg 32 # idata_a[31:0] $end
$var reg 32 $ idata_b[31:0] $end
$var reg 1 % idata_en $end
$var reg 32 & odata[31:0] $end
$var reg 1 ' odata_en $end
$var reg 1 ( stop_the_clock $end
$scope module uut $end
$var reg 1 ) clk $end
$var reg 1 * reset $end
$var reg 32 + idata_a[31:0] $end
$var reg 32 , idata_b[31:0] $end
$var reg 1 - idata_en $end
$var reg 32 . odata[31:0] $end
$var reg 1 / odata_en $end
$comment current_state is not handled $end
$comment next_state is not handled $end
$var reg 32 0 a[31:0] $end
$var reg 32 1 b[31:0] $end
$var reg 32 2 a1[31:0] $end
$var reg 32 3 b1[31:0] $end
$upscope $end
$upscope $end
$enddefinitions $end
#0
0!
1"
b00000000000000000000000000000000 #
b00000000000000000000000000000000 $
0%
b00000000000000000000000000000000 &
0'
0(
0)
1*
b00000000000000000000000000000000 +
b00000000000000000000000000000000 ,
0-
b00000000000000000000000000000000 .
0/
b00000000000000000000000000000000 0
b00000000000000000000000000000000 1
bUUUUUUUUUUUUUUUUUUUUUUUUUUUUUUUU 2
bUUUUUUUUUUUUUUUUUUUUUUUUUUUUUUUU 3
#5000000
1!
0"
1)
0*
#10000000
0!
b00000000000000000000000000001010 $
1%
0)
b00000000000000000000000000001010 ,
1-
b00000000000000000000000000001010 1
b00000000000000000000000000000000 2
b00000000000000000000000000001010 3
#15000000
1!
1)
#20000000
0!
0%
0)
0-
#25000000
1!
b00000000000000000000000000001010 &
1)
b00000000000000000000000000001010 .
b00000000000000000000000000001010 0
#30000000
0!
0)
#35000000
1!
1'
1)
1/
#40000000
0!
b00000000000000000000000000001010 #
b00000000000000000000000000000000 $
1%
0)
b00000000000000000000000000001010 +
b00000000000000000000000000000000 ,
1-
#45000000
1!
0'
1)
0/
b00000000000000000000000000000000 1
b00000000000000000000000000001010 2
b00000000000000000000000000000000 3
#50000000
0!
0%
0)
0-
#55000000
1!
1)
#60000000
0!
0)
#65000000
1!
1)
b00000000000000000000000000001010 1
#70000000
0!
0)
#75000000
1!
1'
1)
1/
#80000000
0!
b00000000000000000000000000101000 #
b00000000000000000000000000011000 $
1%
0)
b00000000000000000000000000101000 +
b00000000000000000000000000011000 ,
1-
#85000000
1!
b00000000000000000000000000101000 &
0'
1)
b00000000000000000000000000101000 .
0/
b00000000000000000000000000101000 0
b00000000000000000000000000011000 1
b00000000000000000000000000101000 2
b00000000000000000000000000011000 3
#90000000
0!
0%
0)
0-
#95000000
1!
1)
#100000000
0!
0)
#105000000
1!
b00000000000000000000000000010000 &
1)
b00000000000000000000000000010000 .
b00000000000000000000000000010000 0
#110000000
0!
0)
#115000000
1!
1)
b00000000000000000000000000001000 1
#120000000
0!
0)
#125000000
1!
b00000000000000000000000000001000 &
1)
b00000000000000000000000000001000 .
b00000000000000000000000000001000 0
#130000000
0!
0)
#135000000
1!
1'
1)
1/
#140000000
0!
b00000000000000000000000000011000 #
b00000000000000000000000000101000 $
1%
0)
b00000000000000000000000000011000 +
b00000000000000000000000000101000 ,
1-
#145000000
1!
b00000000000000000000000000011000 &
0'
1)
b00000000000000000000000000011000 .
0/
b00000000000000000000000000011000 0
b00000000000000000000000000101000 1
b00000000000000000000000000011000 2
b00000000000000000000000000101000 3
#150000000
0!
0%
0)
0-
#155000000
1!
1)
#160000000
0!
0)
#165000000
1!
1)
b00000000000000000000000000010000 1
#170000000
0!
0)
#175000000
1!
b00000000000000000000000000001000 &
1)
b00000000000000000000000000001000 .
b00000000000000000000000000001000 0
#180000000
0!
0)
#185000000
1!
1)
b00000000000000000000000000001000 1
#190000000
0!
0)
#195000000
1!
1'
1)
1/
#200000000
0!
b00000000000000000000000000000111 #
b00000000000000000000000000001101 $
1%
0)
b00000000000000000000000000000111 +
b00000000000000000000000000001101 ,
1-
#205000000
1!
b00000000000000000000000000000111 &
0'
1)
b00000000000000000000000000000111 .
0/
b00000000000000000000000000000111 0
b00000000000000000000000000001101 1
b00000000000000000000000000000111 2
b00000000000000000000000000001101 3
#210000000
0!
0%
0)
0-
#215000000
1!
1)
#220000000
0!
0)
#225000000
1!
1)
b00000000000000000000000000000110 1
#230000000
0!
0)
#235000000
1!
b00000000000000000000000000000001 &
1)
b00000000000000000000000000000001 .
b00000000000000000000000000000001 0
#240000000
0!
0)
#245000000
1!
1)
b00000000000000000000000000000101 1
#250000000
0!
0)
#255000000
1!
1)
b00000000000000000000000000000100 1
#260000000
0!
0)
#265000000
1!
1)
b00000000000000000000000000000011 1
#270000000
0!
0)
#275000000
1!
1)
b00000000000000000000000000000010 1
#280000000
0!
0)
#285000000
1!
1)
b00000000000000000000000000000001 1
#290000000
0!
0)
#295000000
1!
1'
1)
1/
#300000000
0!
b00000000000000000000000000000000 #
b00000000000000000000000000000000 $
1%
0)
b00000000000000000000000000000000 +
b00000000000000000000000000000000 ,
1-
#305000000
1!
b00000000000000000000000000000000 &
0'
1)
b00000000000000000000000000000000 .
0/
b00000000000000000000000000000000 0
b00000000000000000000000000000000 1
b00000000000000000000000000000000 2
b00000000000000000000000000000000 3
#310000000
0!
0%
0)
0-
#315000000
1!
1)
#320000000
0!
0)
#325000000
1!
1'
1)
1/
#330000000
0!
0)
#335000000
1!
0'
1)
0/
